setup.cfg
setup.py
stalin/__init__.py
stalin/проверка элементов.py
stalin/работа_с_файлами.py
stalin/терминал.py
stalin.egg-info/PKG-INFO
stalin.egg-info/SOURCES.txt
stalin.egg-info/dependency_links.txt
stalin.egg-info/not-zip-safe
stalin.egg-info/top_level.txt