Metadata-Version: 2.1
Name: stalin
Version: 0.1
Summary: Мои личные инструменты
Author-email: kolomna.student.8122@gmail.com
